gcscontents/__init__.py
gcscontents/chunks.py
gcscontents/gcloudmanager.py
gcscontents/generic_fs.py
gcscontents/genericfsmanager.py
gcscontents/nbimports.py
gcscontents-0.0.1.dist-info/LICENSE
gcscontents-0.0.1.dist-info/METADATA
gcscontents-0.0.1.dist-info/WHEEL
gcscontents-0.0.1.dist-info/top_level.txt
gcscontents-0.0.1.dist-info/RECORD
