Metadata-Version: 2.1
Name: gcscontents
Version: 0.0.1
Summary: A ContentsManager for managing Google Cloud APIs.
Home-page: https://github.com/sanskar1991/gcscontents
Author: Sanskar Jain
Author-email: <email@root.com>
License: UNKNOWN
Keywords: python,jupyter,contents manager
Platform: UNKNOWN
Classifier: Development Status :: 1 - Planning
Classifier: Programming Language :: Python :: 3.7
Classifier: Programming Language :: Python :: 3.8
Classifier: Operating System :: OS Independent
Classifier: License :: OSI Approved :: MIT License
Requires-Python: >=3.7
Requires-Dist: notebook (>=5.6)
Requires-Dist: nbformat (>=5.0.0)
Requires-Dist: tornado (>=6)
Requires-Dist: traitlets (>=5.0.0)
Requires-Dist: requests
Requires-Dist: gcsfs (>=0.2.1)
Requires-Dist: nose
Provides-Extra: dev
Requires-Dist: setuptools ; extra == 'dev'
Requires-Dist: pylint ; extra == 'dev'
Requires-Dist: flake8 ; extra == 'dev'
Requires-Dist: black ; extra == 'dev'
Requires-Dist: isort ; extra == 'dev'
Requires-Dist: twine ; extra == 'dev'
Requires-Dist: wheel ; extra == 'dev'
Requires-Dist: pytest ; extra == 'dev'
Requires-Dist: pytest-cov ; extra == 'dev'
Requires-Dist: notebook ; extra == 'dev'
Requires-Dist: requests ; extra == 'dev'
Requires-Dist: gcsfs ; extra == 'dev'
Requires-Dist: mock ; extra == 'dev'
Provides-Extra: test
Requires-Dist: pytest ; extra == 'test'
Requires-Dist: pytest-cov ; extra == 'test'
Requires-Dist: toml ; extra == 'test'
